{
    "cfg": {
        "name": "ACO 3 (seq. with local search)",
        "save_name": "ACO_3",
        "class": "ACO_for_VRP_3",
        "params": {
            "ants": 10,
            "iterations": 10,
            "alpha": 1,
            "beta": 2,
            "evaporation": 0.05,
            "patience": 200
        }
    },
    "cost": 91239.207798,
    "vehicles": [
        {
            "id": 0,
            "route": "0->1->18->4->17->0",
            "capacity": 300,
            "filling": 282,
            "duration": 0
        },
        {
            "id": 1,
            "route": "0->6->5->19->21->14->8->0",
            "capacity": 300,
            "filling": 269,
            "duration": 0
        },
        {
            "id": 2,
            "route": "0->2->11->3->7->24->23->10->22->0",
            "capacity": 500,
            "filling": 462,
            "duration": 0
        },
        {
            "id": 3,
            "route": "0->12->9->15->13->16->20->0",
            "capacity": 500,
            "filling": 248,
            "duration": 0
        }
    ]
}