{
    "cfg": {
        "name": "ACO 5 (seq. with depot & gready)",
        "save_name": "ACO_5",
        "class": "ACO_for_VRP_5",
        "params": {
            "ants": 10,
            "iterations": 10,
            "alpha": 1,
            "beta": 2,
            "evaporation": 0.15,
            "patience": 900,
            "patience_small_shake": 80,
            "patience_big_shake": 200,
            "intensity_small_shake": 0.1,
            "intensity_big_shake": 0.3,
            "intensity_elite_ant": 0.3,
            "q_pheromone": 1000.0,
            "tau_min": 0.01,
            "tau_max": 10.0
        }
    },
    "cost": 79103.57367,
    "vehicles": [
        {
            "id": 0,
            "route": "0->2->17->11->14->7->0",
            "capacity": 300,
            "filling": 291,
            "duration": 12815.43359
        },
        {
            "id": 1,
            "route": "0->3->22->10->24->8->5->19->13->0",
            "capacity": 300,
            "filling": 292,
            "duration": 24166.745296999998
        },
        {
            "id": 2,
            "route": "0->9->1->15->12->20->16->21->6->0",
            "capacity": 500,
            "filling": 431,
            "duration": 23475.175005999998
        },
        {
            "id": 3,
            "route": "0->4->23->18->0",
            "capacity": 500,
            "filling": 247,
            "duration": 18646.219777
        },
        {
            "id": 4,
            "route": "0->0",
            "capacity": 700,
            "filling": 0,
            "duration": 0.0
        }
    ]
}